asana_tasker/__init__.py
asana_tasker/asana_task.py
asana_tasker-1.1.1.dist-info/METADATA
asana_tasker-1.1.1.dist-info/WHEEL
asana_tasker-1.1.1.dist-info/top_level.txt
asana_tasker-1.1.1.dist-info/RECORD
