Metadata-Version: 2.4
Name: asana-tasker
Version: 1.1.1
Summary: Simple Asana task creation utility
Author: Yash Soni
Classifier: Programming Language :: Python :: 3
Classifier: License :: OSI Approved :: MIT License
Requires-Dist: requests
Dynamic: author
Dynamic: classifier
Dynamic: requires-dist
Dynamic: summary
